Metadata-Version: 2.4
Name: pii-redact
Version: 0.1.0
Summary: A tool for redacting PII information from text using LLMs
Author-email: Andie Jones <andie@openpipe.ai>
License: MIT License
Project-URL: Homepage, https://github.com/OpenPipe/pii-redaction
Classifier: Programming Language :: Python :: 3
Classifier: License :: OSI Approved :: MIT License
Classifier: Operating System :: OS Independent
Requires-Python: >=3.7
License-File: LICENSE
Requires-Dist: torch>=1.10.0
Requires-Dist: transformers>=4.26.0
Requires-Dist: tqdm>=4.61.0
Requires-Dist: faker>=8.0.0
Dynamic: license-file
